{
  "id": "Udacity Courses/Intermediate Python/meme-generator",
  "title": "Project: Meme Generator",
  "description": "The project for this course is a meme generator, an application you'll write in Python that will pair random images with random quotes.",
  "source": "@site/docs/Udacity Courses/Intermediate Python/meme-generator.md",
  "sourceDirName": "Udacity Courses/Intermediate Python",
  "slug": "/Udacity Courses/Intermediate Python/meme-generator",
  "permalink": "/Udacity Courses/Intermediate Python/meme-generator",
  "draft": false,
  "unlisted": false,
  "tags": [],
  "version": "current",
  "sidebarPosition": 30,
  "frontMatter": {
    "sidebar_position": 30,
    "sidebar_label": "Project: Meme Generator"
  },
  "sidebar": "tutorialSidebar",
  "previous": {
    "title": "Project: Exploring Near-Earth Objects",
    "permalink": "/Udacity Courses/Intermediate Python/near-earth-objects"
  },
  "next": {
    "title": "React",
    "permalink": "/category/react"
  }
}